[{"year":1910,"n":5,"prop":0},{"year":1915,"n":6,"prop":0.00000586},{"year":1916,"n":10,"prop":0.00000921},{"year":1917,"n":8,"prop":0.00000712},{"year":1918,"n":7,"prop":0.00000582},{"year":1919,"n":5,"prop":0.00000426},{"year":1920,"n":11,"prop":0.00000884},{"year":1921,"n":7,"prop":0.00000547},{"year":1922,"n":14,"prop":0},{"year":1923,"n":13,"prop":0},{"year":1924,"n":8,"prop":0.00000617},{"year":1925,"n":13,"prop":0},{"year":1926,"n":7,"prop":0.00000569},{"year":1927,"n":6,"prop":0.00000485},{"year":1928,"n":13,"prop":0},{"year":1929,"n":7,"prop":0.00000605},{"year":1930,"n":17,"prop":0},{"year":1931,"n":15,"prop":0},{"year":1932,"n":12,"prop":0},{"year":1933,"n":13,"prop":0},{"year":1934,"n":9,"prop":0.00000832},{"year":1935,"n":8,"prop":0.00000736},{"year":1936,"n":10,"prop":0.00000928},{"year":1937,"n":14,"prop":0},{"year":1938,"n":12,"prop":0},{"year":1939,"n":11,"prop":0.0000097},{"year":1940,"n":15,"prop":0},{"year":1941,"n":11,"prop":0.00000883},{"year":1942,"n":12,"prop":0.00000863},{"year":1943,"n":16,"prop":0},{"year":1945,"n":6,"prop":0.00000446},{"year":1946,"n":7,"prop":0.00000434},{"year":1947,"n":15,"prop":0.00000825},{"year":1948,"n":12,"prop":0.00000689},{"year":1950,"n":9,"prop":0.00000512},{"year":1951,"n":5,"prop":0.00000271},{"year":1952,"n":15,"prop":0.00000789},{"year":1953,"n":6,"prop":0.00000311},{"year":1954,"n":6,"prop":0.00000301},{"year":1955,"n":7,"prop":0.00000349},{"year":1956,"n":6,"prop":0.00000291},{"year":1958,"n":7,"prop":0.00000339},{"year":1959,"n":6,"prop":0.00000289},{"year":1962,"n":5,"prop":0.00000247},{"year":1976,"n":5,"prop":0.00000318},{"year":2005,"n":5,"prop":0.00000247},{"year":2006,"n":6,"prop":0.00000287},{"year":2008,"n":5,"prop":0.0000024},{"year":2009,"n":7,"prop":0.00000346},{"year":2011,"n":5,"prop":0.00000258},{"year":2012,"n":6,"prop":0.0000031},{"year":2014,"n":5,"prop":0.00000256},{"year":2016,"n":5,"prop":0.00000259}]