[{"year":1880,"n":783,"prop":0.008},{"year":1881,"n":737,"prop":0.0075},{"year":1882,"n":811,"prop":0.007},{"year":1883,"n":875,"prop":0.0073},{"year":1884,"n":935,"prop":0.0068},{"year":1885,"n":1062,"prop":0.0075},{"year":1886,"n":1061,"prop":0.0069},{"year":1887,"n":1043,"prop":0.0067},{"year":1888,"n":1292,"prop":0.0068},{"year":1889,"n":1201,"prop":0.0063},{"year":1890,"n":1275,"prop":0.0063},{"year":1891,"n":1200,"prop":0.0061},{"year":1892,"n":1360,"prop":0.006},{"year":1893,"n":1367,"prop":0.0061},{"year":1894,"n":1320,"prop":0.0056},{"year":1895,"n":1380,"prop":0.0056},{"year":1896,"n":1407,"prop":0.0056},{"year":1897,"n":1380,"prop":0.0056},{"year":1898,"n":1462,"prop":0.0053},{"year":1899,"n":1297,"prop":0.0052},{"year":1900,"n":1766,"prop":0.0056},{"year":1901,"n":1362,"prop":0.0054},{"year":1902,"n":1501,"prop":0.0054},{"year":1903,"n":1447,"prop":0.0052},{"year":1904,"n":1426,"prop":0.0049},{"year":1905,"n":1642,"prop":0.0053},{"year":1906,"n":1603,"prop":0.0051},{"year":1907,"n":1680,"prop":0.005},{"year":1908,"n":1749,"prop":0.0049},{"year":1909,"n":1931,"prop":0.0052},{"year":1910,"n":2074,"prop":0.0049},{"year":1911,"n":2158,"prop":0.0049},{"year":1912,"n":2825,"prop":0.0048},{"year":1913,"n":3195,"prop":0.0049},{"year":1914,"n":3813,"prop":0.0048},{"year":1915,"n":4831,"prop":0.0047},{"year":1916,"n":5066,"prop":0.0047},{"year":1917,"n":5078,"prop":0.0045},{"year":1918,"n":5267,"prop":0.0044},{"year":1919,"n":4950,"prop":0.0042},{"year":1920,"n":4889,"prop":0.0039},{"year":1921,"n":4737,"prop":0.0037},{"year":1922,"n":4616,"prop":0.0037},{"year":1923,"n":4323,"prop":0.0035},{"year":1924,"n":4289,"prop":0.0033},{"year":1925,"n":4047,"prop":0.0032},{"year":1926,"n":3687,"prop":0.003},{"year":1927,"n":3586,"prop":0.0029},{"year":1928,"n":3206,"prop":0.0027},{"year":1929,"n":2950,"prop":0.0025},{"year":1930,"n":2879,"prop":0.0025},{"year":1931,"n":2624,"prop":0.0024},{"year":1932,"n":2657,"prop":0.0024},{"year":1933,"n":2401,"prop":0.0023},{"year":1934,"n":2357,"prop":0.0022},{"year":1935,"n":2343,"prop":0.0022},{"year":1936,"n":2279,"prop":0.0021},{"year":1937,"n":2283,"prop":0.0021},{"year":1938,"n":2476,"prop":0.0022},{"year":1939,"n":2637,"prop":0.0023},{"year":1940,"n":2706,"prop":0.0023},{"year":1941,"n":2846,"prop":0.0023},{"year":1942,"n":2904,"prop":0.0021},{"year":1943,"n":2972,"prop":0.0021},{"year":1944,"n":2687,"prop":0.002},{"year":1945,"n":2327,"prop":0.0017},{"year":1946,"n":2796,"prop":0.0017},{"year":1947,"n":2954,"prop":0.0016},{"year":1948,"n":2776,"prop":0.0016},{"year":1949,"n":2923,"prop":0.0017},{"year":1950,"n":2727,"prop":0.0016},{"year":1951,"n":2747,"prop":0.0015},{"year":1952,"n":2783,"prop":0.0015},{"year":1953,"n":2973,"prop":0.0015},{"year":1954,"n":3155,"prop":0.0016},{"year":1955,"n":3288,"prop":0.0016},{"year":1956,"n":3321,"prop":0.0016},{"year":1957,"n":3688,"prop":0.0018},{"year":1958,"n":3836,"prop":0.0019},{"year":1959,"n":3936,"prop":0.0019},{"year":1960,"n":3785,"prop":0.0018},{"year":1961,"n":3905,"prop":0.0019},{"year":1962,"n":3751,"prop":0.0019},{"year":1963,"n":3571,"prop":0.0018},{"year":1964,"n":3539,"prop":0.0018},{"year":1965,"n":3100,"prop":0.0017},{"year":1966,"n":3045,"prop":0.0017},{"year":1967,"n":2774,"prop":0.0016},{"year":1968,"n":2993,"prop":0.0018},{"year":1969,"n":3714,"prop":0.0021},{"year":1970,"n":3179,"prop":0.0017},{"year":1971,"n":2604,"prop":0.0015},{"year":1972,"n":2335,"prop":0.0014},{"year":1973,"n":2092,"prop":0.0013},{"year":1974,"n":2065,"prop":0.0013},{"year":1975,"n":2005,"prop":0.0013},{"year":1976,"n":1915,"prop":0.0012},{"year":1977,"n":2065,"prop":0.0013},{"year":1978,"n":2593,"prop":0.0016},{"year":1979,"n":2567,"prop":0.0015},{"year":1980,"n":3068,"prop":0.0017},{"year":1981,"n":3669,"prop":0.0021},{"year":1982,"n":3502,"prop":0.0019},{"year":1983,"n":3383,"prop":0.0019},{"year":1984,"n":3360,"prop":0.0019},{"year":1985,"n":3204,"prop":0.0017},{"year":1986,"n":3106,"prop":0.0017},{"year":1987,"n":3329,"prop":0.0018},{"year":1988,"n":3359,"prop":0.0017},{"year":1989,"n":3369,"prop":0.0017},{"year":1990,"n":3910,"prop":0.0019},{"year":1991,"n":5363,"prop":0.0026},{"year":1992,"n":5021,"prop":0.0025},{"year":1993,"n":4659,"prop":0.0024},{"year":1994,"n":4841,"prop":0.0025},{"year":1995,"n":5411,"prop":0.0028},{"year":1996,"n":6312,"prop":0.0033},{"year":1997,"n":7339,"prop":0.0038},{"year":1998,"n":8327,"prop":0.0043},{"year":1999,"n":8751,"prop":0.0045},{"year":2000,"n":8766,"prop":0.0044},{"year":2001,"n":8837,"prop":0.0045},{"year":2002,"n":7963,"prop":0.004},{"year":2003,"n":7434,"prop":0.0037},{"year":2004,"n":7145,"prop":0.0035},{"year":2005,"n":7085,"prop":0.0035},{"year":2006,"n":6883,"prop":0.0033},{"year":2007,"n":6130,"prop":0.0029},{"year":2008,"n":5616,"prop":0.0027},{"year":2009,"n":4991,"prop":0.0025},{"year":2010,"n":4674,"prop":0.0024},{"year":2011,"n":4347,"prop":0.0022},{"year":2012,"n":3876,"prop":0.002},{"year":2013,"n":3747,"prop":0.0019},{"year":2014,"n":3597,"prop":0.0018},{"year":2015,"n":3371,"prop":0.0017},{"year":2016,"n":3323,"prop":0.0017},{"year":2017,"n":3111,"prop":0.0017}]