[{"year":1974,"n":5,"prop":0.00000319},{"year":1978,"n":5,"prop":0.00000304},{"year":1989,"n":6,"prop":0.00000301},{"year":1991,"n":6,"prop":0.00000295},{"year":1992,"n":5,"prop":0.00000249},{"year":1993,"n":6,"prop":0.00000304},{"year":1994,"n":12,"prop":0.00000616},{"year":1995,"n":7,"prop":0.00000364},{"year":1996,"n":17,"prop":0.00000887},{"year":1997,"n":15,"prop":0.00000786},{"year":1998,"n":22,"prop":0},{"year":1999,"n":69,"prop":0},{"year":2000,"n":151,"prop":0.0001},{"year":2001,"n":140,"prop":0.0001},{"year":2002,"n":148,"prop":0.0001},{"year":2003,"n":162,"prop":0.0001},{"year":2004,"n":220,"prop":0.0001},{"year":2005,"n":185,"prop":0.0001},{"year":2006,"n":161,"prop":0.0001},{"year":2007,"n":178,"prop":0.0001},{"year":2008,"n":140,"prop":0.0001},{"year":2009,"n":135,"prop":0.0001},{"year":2010,"n":134,"prop":0.0001},{"year":2011,"n":122,"prop":0.0001},{"year":2012,"n":97,"prop":0.0001},{"year":2013,"n":90,"prop":0},{"year":2014,"n":77,"prop":0},{"year":2015,"n":86,"prop":0},{"year":2016,"n":76,"prop":0},{"year":2017,"n":72,"prop":0}]