[{"year":1898,"n":5,"prop":0},{"year":1912,"n":6,"prop":0},{"year":1913,"n":7,"prop":0},{"year":1917,"n":6,"prop":0.00000534},{"year":1918,"n":6,"prop":0.00000499},{"year":1919,"n":15,"prop":0},{"year":1920,"n":7,"prop":0.00000563},{"year":1921,"n":9,"prop":0.00000703},{"year":1922,"n":8,"prop":0.00000641},{"year":1923,"n":12,"prop":0.00000958},{"year":1924,"n":12,"prop":0.00000926},{"year":1925,"n":7,"prop":0.00000554},{"year":1926,"n":7,"prop":0.00000569},{"year":1928,"n":7,"prop":0.00000586},{"year":1930,"n":6,"prop":0.00000514},{"year":1931,"n":7,"prop":0.00000634},{"year":1932,"n":12,"prop":0},{"year":1933,"n":5,"prop":0.00000478},{"year":1936,"n":6,"prop":0.00000557},{"year":1938,"n":6,"prop":0.00000526},{"year":1939,"n":10,"prop":0.00000882},{"year":1946,"n":5,"prop":0.0000031},{"year":1951,"n":5,"prop":0.00000271},{"year":1955,"n":6,"prop":0.00000299},{"year":1960,"n":6,"prop":0.00000288},{"year":1963,"n":7,"prop":0.00000352},{"year":1978,"n":5,"prop":0.00000304}]