[{"year":1885,"n":6,"prop":0},{"year":1888,"n":6,"prop":0},{"year":1889,"n":5,"prop":0},{"year":1892,"n":8,"prop":0},{"year":1896,"n":5,"prop":0},{"year":1899,"n":6,"prop":0},{"year":1902,"n":5,"prop":0},{"year":1905,"n":6,"prop":0},{"year":1906,"n":6,"prop":0},{"year":1907,"n":5,"prop":0},{"year":1910,"n":7,"prop":0},{"year":1912,"n":5,"prop":0.00000852},{"year":1913,"n":11,"prop":0},{"year":1915,"n":11,"prop":0},{"year":1916,"n":5,"prop":0.00000461},{"year":1917,"n":8,"prop":0.00000712},{"year":1918,"n":12,"prop":0.00000998},{"year":1919,"n":6,"prop":0.00000511},{"year":1920,"n":13,"prop":0},{"year":1921,"n":12,"prop":0.00000938},{"year":1922,"n":10,"prop":0.00000802},{"year":1925,"n":8,"prop":0.00000633},{"year":1926,"n":11,"prop":0.00000894},{"year":1927,"n":9,"prop":0.00000728},{"year":1928,"n":10,"prop":0.00000836},{"year":1931,"n":6,"prop":0.00000544},{"year":1932,"n":5,"prop":0.00000452},{"year":1933,"n":8,"prop":0.00000765},{"year":1937,"n":5,"prop":0.00000454},{"year":1950,"n":5,"prop":0.00000284},{"year":1957,"n":5,"prop":0.00000238},{"year":1958,"n":6,"prop":0.00000291},{"year":1959,"n":7,"prop":0.00000337},{"year":1964,"n":7,"prop":0.00000358},{"year":1970,"n":5,"prop":0.00000273},{"year":1977,"n":6,"prop":0.00000365}]