[{"year":1923,"sex":"F","n":7,"prop":0.00000559},{"year":1932,"sex":"F","n":5,"prop":0.00000452},{"year":1998,"sex":"F","n":5,"prop":0.00000258},{"year":1999,"sex":"F","n":13,"prop":0.00000668},{"year":2000,"sex":"F","n":11,"prop":0.00000551},{"year":2001,"sex":"F","n":9,"prop":0.00000455},{"year":2002,"sex":"F","n":12,"prop":0.00000608},{"year":2003,"sex":"F","n":31,"prop":0},{"year":2004,"sex":"F","n":59,"prop":0},{"year":2005,"sex":"F","n":106,"prop":0.0001},{"year":2006,"sex":"F","n":170,"prop":0.0001},{"year":2007,"sex":"F","n":233,"prop":0.0001},{"year":2008,"sex":"F","n":273,"prop":0.0001},{"year":2009,"sex":"F","n":289,"prop":0.0001},{"year":2010,"sex":"F","n":320,"prop":0.0002},{"year":2011,"sex":"F","n":293,"prop":0.0002},{"year":2012,"sex":"F","n":329,"prop":0.0002},{"year":2013,"sex":"F","n":345,"prop":0.0002},{"year":2014,"sex":"F","n":398,"prop":0.0002},{"year":2015,"sex":"F","n":437,"prop":0.0002},{"year":2016,"sex":"F","n":403,"prop":0.0002},{"year":2017,"sex":"F","n":514,"prop":0.0003}]