[{"year":1911,"sex":"F","n":5,"prop":0},{"year":1916,"sex":"F","n":5,"prop":0.00000461},{"year":1917,"sex":"F","n":5,"prop":0.00000445},{"year":1918,"sex":"F","n":6,"prop":0.00000499},{"year":1920,"sex":"F","n":9,"prop":0.00000723},{"year":1921,"sex":"F","n":6,"prop":0.00000469},{"year":1922,"sex":"F","n":7,"prop":0.00000561},{"year":1924,"sex":"F","n":7,"prop":0.0000054},{"year":1925,"sex":"F","n":6,"prop":0.00000475},{"year":1926,"sex":"F","n":5,"prop":0.00000406},{"year":1927,"sex":"F","n":7,"prop":0.00000566},{"year":1928,"sex":"F","n":10,"prop":0.00000836},{"year":1932,"sex":"F","n":6,"prop":0.00000542},{"year":1934,"sex":"F","n":5,"prop":0.00000462},{"year":1944,"sex":"F","n":5,"prop":0.00000366},{"year":2001,"sex":"F","n":5,"prop":0.00000253},{"year":2003,"sex":"F","n":7,"prop":0.00000349},{"year":2004,"sex":"F","n":7,"prop":0.00000347},{"year":2005,"sex":"F","n":18,"prop":0.00000887},{"year":2006,"sex":"F","n":16,"prop":0.00000766},{"year":2007,"sex":"F","n":23,"prop":0},{"year":2008,"sex":"F","n":30,"prop":0},{"year":2009,"sex":"F","n":47,"prop":0},{"year":2010,"sex":"F","n":53,"prop":0},{"year":2011,"sex":"F","n":68,"prop":0},{"year":2012,"sex":"F","n":88,"prop":0},{"year":2013,"sex":"F","n":86,"prop":0},{"year":2014,"sex":"F","n":85,"prop":0},{"year":2015,"sex":"F","n":88,"prop":0},{"year":2016,"sex":"F","n":109,"prop":0.0001},{"year":2017,"sex":"F","n":108,"prop":0.0001}]