[{"year":1994,"sex":"F","n":14,"prop":0.00000718},{"year":1995,"sex":"F","n":21,"prop":0},{"year":1996,"sex":"F","n":15,"prop":0.00000783},{"year":1997,"sex":"F","n":17,"prop":0.00000891},{"year":1998,"sex":"F","n":17,"prop":0.00000877},{"year":1999,"sex":"F","n":22,"prop":0},{"year":2000,"sex":"F","n":18,"prop":0.00000902},{"year":2001,"sex":"F","n":7,"prop":0.00000354},{"year":2002,"sex":"F","n":8,"prop":0.00000405},{"year":2003,"sex":"F","n":11,"prop":0.00000549},{"year":2004,"sex":"F","n":5,"prop":0.00000248}]