[{"year":1952,"sex":"F","n":5,"prop":0.00000263},{"year":1965,"sex":"F","n":5,"prop":0.00000274},{"year":1969,"sex":"F","n":6,"prop":0.0000034},{"year":1974,"sex":"F","n":6,"prop":0.00000383},{"year":1976,"sex":"F","n":5,"prop":0.00000318},{"year":1978,"sex":"F","n":5,"prop":0.00000304},{"year":1984,"sex":"F","n":6,"prop":0.00000333},{"year":1985,"sex":"F","n":5,"prop":0.00000271},{"year":1986,"sex":"F","n":7,"prop":0.00000379},{"year":1989,"sex":"F","n":5,"prop":0.00000251},{"year":1994,"sex":"F","n":5,"prop":0.00000257},{"year":1998,"sex":"F","n":5,"prop":0.00000258},{"year":2006,"sex":"F","n":8,"prop":0.00000383},{"year":2012,"sex":"F","n":5,"prop":0.00000258}]