[{"year":1915,"sex":"F","n":8,"prop":0.00000781},{"year":1917,"sex":"F","n":7,"prop":0.00000623},{"year":1919,"sex":"F","n":6,"prop":0.00000511},{"year":1923,"sex":"F","n":8,"prop":0.00000639},{"year":1923,"sex":"M","n":5,"prop":0.00000442},{"year":1924,"sex":"F","n":8,"prop":0.00000617},{"year":1924,"sex":"M","n":10,"prop":0.00000855},{"year":1925,"sex":"F","n":5,"prop":0.00000396},{"year":1925,"sex":"M","n":7,"prop":0.00000608},{"year":1926,"sex":"M","n":10,"prop":0.00000873},{"year":1928,"sex":"M","n":5,"prop":0.00000438},{"year":1929,"sex":"F","n":8,"prop":0.00000691},{"year":1929,"sex":"M","n":8,"prop":0.00000722},{"year":1932,"sex":"M","n":6,"prop":0.00000559},{"year":1934,"sex":"M","n":6,"prop":0.00000565},{"year":1935,"sex":"M","n":5,"prop":0.00000468},{"year":1936,"sex":"M","n":7,"prop":0.00000658},{"year":1939,"sex":"M","n":6,"prop":0.00000529},{"year":1943,"sex":"M","n":6,"prop":0.00000413},{"year":1946,"sex":"M","n":6,"prop":0.00000364},{"year":1953,"sex":"M","n":6,"prop":0.000003},{"year":1955,"sex":"M","n":7,"prop":0.00000335},{"year":1956,"sex":"M","n":6,"prop":0.0000028},{"year":1961,"sex":"M","n":5,"prop":0.00000232},{"year":1963,"sex":"M","n":6,"prop":0.00000291},{"year":1969,"sex":"M","n":7,"prop":0.00000383},{"year":1975,"sex":"M","n":5,"prop":0.00000308},{"year":1977,"sex":"M","n":5,"prop":0.00000292},{"year":1980,"sex":"M","n":7,"prop":0.00000377},{"year":1982,"sex":"M","n":9,"prop":0.00000477},{"year":1985,"sex":"M","n":5,"prop":0.0000026},{"year":1988,"sex":"M","n":5,"prop":0.0000025}]