[{"year":1947,"sex":"F","n":5,"prop":0.00000275},{"year":1948,"sex":"F","n":5,"prop":0.00000287},{"year":1950,"sex":"F","n":10,"prop":0.00000569},{"year":1951,"sex":"F","n":11,"prop":0.00000595},{"year":1952,"sex":"F","n":9,"prop":0.00000473},{"year":1953,"sex":"F","n":9,"prop":0.00000467},{"year":1954,"sex":"F","n":16,"prop":0.00000804},{"year":1955,"sex":"F","n":19,"prop":0.00000948},{"year":1956,"sex":"F","n":16,"prop":0.00000777},{"year":1957,"sex":"F","n":17,"prop":0.0000081},{"year":1958,"sex":"F","n":15,"prop":0.00000726},{"year":1959,"sex":"F","n":13,"prop":0.00000625},{"year":1960,"sex":"F","n":15,"prop":0.00000721},{"year":1961,"sex":"F","n":14,"prop":0.00000674},{"year":1962,"sex":"F","n":11,"prop":0.00000543},{"year":1963,"sex":"F","n":17,"prop":0.00000855},{"year":1965,"sex":"F","n":10,"prop":0.00000547},{"year":1966,"sex":"F","n":8,"prop":0.00000456},{"year":1967,"sex":"F","n":5,"prop":0.00000291},{"year":1968,"sex":"F","n":6,"prop":0.00000351}]