[{"year":1986,"sex":"F","n":5,"prop":0.00000271},{"year":1988,"sex":"F","n":6,"prop":0.00000312},{"year":1989,"sex":"F","n":13,"prop":0.00000653},{"year":1990,"sex":"F","n":14,"prop":0.00000682},{"year":1991,"sex":"F","n":12,"prop":0.0000059},{"year":1992,"sex":"F","n":13,"prop":0.00000649},{"year":1993,"sex":"F","n":6,"prop":0.00000304},{"year":1994,"sex":"F","n":6,"prop":0.00000308},{"year":1995,"sex":"F","n":8,"prop":0.00000416},{"year":1996,"sex":"F","n":12,"prop":0.00000626},{"year":1997,"sex":"F","n":9,"prop":0.00000471},{"year":1998,"sex":"F","n":8,"prop":0.00000413},{"year":1999,"sex":"F","n":6,"prop":0.00000308},{"year":2001,"sex":"F","n":5,"prop":0.00000253},{"year":2002,"sex":"F","n":5,"prop":0.00000253},{"year":2006,"sex":"F","n":5,"prop":0.00000239}]