[{"year":1899,"sex":"M","n":5,"prop":0},{"year":1900,"sex":"M","n":8,"prop":0},{"year":1901,"sex":"M","n":7,"prop":0.0001},{"year":1902,"sex":"M","n":8,"prop":0.0001},{"year":1903,"sex":"M","n":5,"prop":0},{"year":1904,"sex":"M","n":6,"prop":0},{"year":1905,"sex":"M","n":7,"prop":0},{"year":1906,"sex":"M","n":6,"prop":0},{"year":1908,"sex":"M","n":8,"prop":0},{"year":1909,"sex":"M","n":6,"prop":0},{"year":1910,"sex":"M","n":5,"prop":0},{"year":1911,"sex":"M","n":5,"prop":0},{"year":1912,"sex":"M","n":6,"prop":0},{"year":1913,"sex":"M","n":13,"prop":0},{"year":1914,"sex":"M","n":25,"prop":0},{"year":1915,"sex":"M","n":23,"prop":0},{"year":1916,"sex":"M","n":21,"prop":0},{"year":1917,"sex":"M","n":32,"prop":0},{"year":1918,"sex":"M","n":25,"prop":0},{"year":1919,"sex":"M","n":29,"prop":0},{"year":1920,"sex":"M","n":36,"prop":0},{"year":1921,"sex":"M","n":40,"prop":0},{"year":1922,"sex":"M","n":38,"prop":0},{"year":1923,"sex":"M","n":24,"prop":0},{"year":1924,"sex":"M","n":26,"prop":0},{"year":1925,"sex":"M","n":26,"prop":0},{"year":1926,"sex":"M","n":29,"prop":0},{"year":1927,"sex":"M","n":31,"prop":0},{"year":1928,"sex":"M","n":24,"prop":0},{"year":1929,"sex":"M","n":28,"prop":0},{"year":1930,"sex":"M","n":26,"prop":0},{"year":1931,"sex":"M","n":24,"prop":0},{"year":1932,"sex":"M","n":24,"prop":0},{"year":1933,"sex":"M","n":35,"prop":0},{"year":1934,"sex":"M","n":18,"prop":0},{"year":1935,"sex":"M","n":41,"prop":0},{"year":1936,"sex":"M","n":72,"prop":0.0001},{"year":1937,"sex":"M","n":70,"prop":0.0001},{"year":1938,"sex":"M","n":267,"prop":0.0002},{"year":1939,"sex":"M","n":291,"prop":0.0003},{"year":1940,"sex":"M","n":254,"prop":0.0002},{"year":1941,"sex":"M","n":247,"prop":0.0002},{"year":1942,"sex":"M","n":338,"prop":0.0002},{"year":1943,"sex":"M","n":294,"prop":0.0002},{"year":1944,"sex":"M","n":404,"prop":0.0003},{"year":1945,"sex":"M","n":401,"prop":0.0003},{"year":1946,"sex":"M","n":414,"prop":0.0003},{"year":1947,"sex":"M","n":604,"prop":0.0003},{"year":1948,"sex":"M","n":609,"prop":0.0003},{"year":1949,"sex":"M","n":616,"prop":0.0003},{"year":1950,"sex":"M","n":735,"prop":0.0004},{"year":1951,"sex":"M","n":752,"prop":0.0004},{"year":1952,"sex":"M","n":708,"prop":0.0004},{"year":1953,"sex":"M","n":711,"prop":0.0004},{"year":1954,"sex":"M","n":922,"prop":0.0004},{"year":1955,"sex":"M","n":1055,"prop":0.0005},{"year":1956,"sex":"F","n":6,"prop":0.00000291},{"year":1956,"sex":"M","n":1115,"prop":0.0005},{"year":1957,"sex":"F","n":5,"prop":0.00000238},{"year":1957,"sex":"M","n":1159,"prop":0.0005},{"year":1958,"sex":"M","n":1131,"prop":0.0005},{"year":1959,"sex":"F","n":6,"prop":0.00000289},{"year":1959,"sex":"M","n":1431,"prop":0.0007},{"year":1960,"sex":"F","n":8,"prop":0.00000385},{"year":1960,"sex":"M","n":1876,"prop":0.0009},{"year":1961,"sex":"M","n":1805,"prop":0.0008},{"year":1962,"sex":"F","n":5,"prop":0.00000247},{"year":1962,"sex":"M","n":2003,"prop":0.001},{"year":1963,"sex":"F","n":7,"prop":0.00000352},{"year":1963,"sex":"M","n":1873,"prop":0.0009},{"year":1964,"sex":"F","n":8,"prop":0.00000409},{"year":1964,"sex":"M","n":2089,"prop":0.001},{"year":1965,"sex":"F","n":9,"prop":0.00000493},{"year":1965,"sex":"M","n":1752,"prop":0.0009},{"year":1966,"sex":"M","n":1818,"prop":0.001},{"year":1967,"sex":"F","n":8,"prop":0.00000466},{"year":1967,"sex":"M","n":1806,"prop":0.001},{"year":1968,"sex":"F","n":14,"prop":0.00000819},{"year":1968,"sex":"M","n":1995,"prop":0.0011},{"year":1969,"sex":"F","n":9,"prop":0.00000511},{"year":1969,"sex":"M","n":3030,"prop":0.0017},{"year":1970,"sex":"F","n":13,"prop":0.0000071},{"year":1970,"sex":"M","n":4166,"prop":0.0022},{"year":1971,"sex":"F","n":15,"prop":0.00000856},{"year":1971,"sex":"M","n":3180,"prop":0.0017},{"year":1972,"sex":"F","n":17,"prop":0},{"year":1972,"sex":"M","n":2254,"prop":0.0013},{"year":1973,"sex":"F","n":15,"prop":0.00000965},{"year":1973,"sex":"M","n":1686,"prop":0.001},{"year":1974,"sex":"F","n":7,"prop":0.00000447},{"year":1974,"sex":"M","n":1529,"prop":0.0009},{"year":1975,"sex":"M","n":1498,"prop":0.0009},{"year":1976,"sex":"F","n":8,"prop":0.00000509},{"year":1976,"sex":"M","n":1737,"prop":0.0011},{"year":1977,"sex":"F","n":14,"prop":0.00000851},{"year":1977,"sex":"M","n":1927,"prop":0.0011},{"year":1978,"sex":"F","n":11,"prop":0.00000669},{"year":1978,"sex":"M","n":1973,"prop":0.0012},{"year":1979,"sex":"F","n":22,"prop":0},{"year":1979,"sex":"M","n":1871,"prop":0.001},{"year":1980,"sex":"F","n":15,"prop":0.00000843},{"year":1980,"sex":"M","n":1786,"prop":0.001},{"year":1981,"sex":"F","n":11,"prop":0.00000615},{"year":1981,"sex":"M","n":1685,"prop":0.0009},{"year":1982,"sex":"F","n":14,"prop":0.00000772},{"year":1982,"sex":"M","n":1972,"prop":0.001},{"year":1983,"sex":"F","n":11,"prop":0.00000615},{"year":1983,"sex":"M","n":1962,"prop":0.0011},{"year":1984,"sex":"F","n":15,"prop":0.00000832},{"year":1984,"sex":"M","n":2137,"prop":0.0011},{"year":1985,"sex":"F","n":8,"prop":0.00000433},{"year":1985,"sex":"M","n":2152,"prop":0.0011},{"year":1986,"sex":"F","n":11,"prop":0.00000596},{"year":1986,"sex":"M","n":2051,"prop":0.0011},{"year":1987,"sex":"F","n":11,"prop":0.00000587},{"year":1987,"sex":"M","n":1992,"prop":0.001},{"year":1988,"sex":"F","n":10,"prop":0.0000052},{"year":1988,"sex":"M","n":1892,"prop":0.0009},{"year":1989,"sex":"F","n":15,"prop":0.00000753},{"year":1989,"sex":"M","n":1822,"prop":0.0009},{"year":1990,"sex":"F","n":5,"prop":0.00000243},{"year":1990,"sex":"M","n":1695,"prop":0.0008},{"year":1991,"sex":"F","n":7,"prop":0.00000344},{"year":1991,"sex":"M","n":1575,"prop":0.0007},{"year":1992,"sex":"M","n":1507,"prop":0.0007},{"year":1993,"sex":"M","n":1259,"prop":0.0006},{"year":1994,"sex":"M","n":1120,"prop":0.0005},{"year":1995,"sex":"M","n":1094,"prop":0.0005},{"year":1996,"sex":"M","n":1048,"prop":0.0005},{"year":1997,"sex":"M","n":918,"prop":0.0005},{"year":1998,"sex":"M","n":880,"prop":0.0004},{"year":1999,"sex":"M","n":1003,"prop":0.0005},{"year":2000,"sex":"M","n":1221,"prop":0.0006},{"year":2001,"sex":"M","n":1285,"prop":0.0006},{"year":2002,"sex":"M","n":1232,"prop":0.0006},{"year":2003,"sex":"M","n":1167,"prop":0.0006},{"year":2004,"sex":"F","n":5,"prop":0.00000248},{"year":2004,"sex":"M","n":1161,"prop":0.0005},{"year":2005,"sex":"M","n":1255,"prop":0.0006},{"year":2006,"sex":"M","n":1002,"prop":0.0005},{"year":2007,"sex":"M","n":826,"prop":0.0004},{"year":2008,"sex":"M","n":750,"prop":0.0003},{"year":2009,"sex":"M","n":639,"prop":0.0003},{"year":2010,"sex":"M","n":602,"prop":0.0003},{"year":2011,"sex":"M","n":575,"prop":0.0003},{"year":2012,"sex":"M","n":539,"prop":0.0003},{"year":2013,"sex":"M","n":458,"prop":0.0002},{"year":2014,"sex":"M","n":509,"prop":0.0002},{"year":2015,"sex":"M","n":454,"prop":0.0002},{"year":2016,"sex":"M","n":433,"prop":0.0002},{"year":2017,"sex":"M","n":404,"prop":0.0002}]