[{"year":1957,"sex":"F","n":5,"prop":0.00000238},{"year":1958,"sex":"F","n":6,"prop":0.00000291},{"year":1959,"sex":"F","n":6,"prop":0.00000289},{"year":1961,"sex":"F","n":6,"prop":0.00000289},{"year":1962,"sex":"F","n":5,"prop":0.00000247},{"year":1963,"sex":"F","n":9,"prop":0.00000453},{"year":1964,"sex":"F","n":6,"prop":0.00000307},{"year":1965,"sex":"F","n":7,"prop":0.00000383},{"year":1967,"sex":"F","n":8,"prop":0.00000466},{"year":1968,"sex":"F","n":8,"prop":0.00000468},{"year":1969,"sex":"F","n":11,"prop":0.00000624},{"year":1970,"sex":"F","n":5,"prop":0.00000273},{"year":1971,"sex":"F","n":7,"prop":0.00000399},{"year":1972,"sex":"F","n":6,"prop":0.00000372},{"year":1978,"sex":"F","n":5,"prop":0.00000304},{"year":1979,"sex":"F","n":5,"prop":0.0000029}]