[{"year":1999,"sex":"F","n":5,"prop":0.00000257},{"year":2002,"sex":"F","n":7,"prop":0.00000355},{"year":2005,"sex":"F","n":7,"prop":0.00000345},{"year":2006,"sex":"F","n":6,"prop":0.00000287},{"year":2008,"sex":"F","n":5,"prop":0.0000024},{"year":2009,"sex":"F","n":9,"prop":0.00000445},{"year":2010,"sex":"F","n":9,"prop":0.0000046},{"year":2011,"sex":"F","n":7,"prop":0.00000362},{"year":2012,"sex":"F","n":9,"prop":0.00000465},{"year":2014,"sex":"F","n":7,"prop":0.00000359},{"year":2015,"sex":"F","n":7,"prop":0.0000036},{"year":2016,"sex":"F","n":13,"prop":0.00000674},{"year":2017,"sex":"F","n":9,"prop":0.0000048}]