[{"year":1918,"sex":"F","n":5,"prop":0.00000416},{"year":1923,"sex":"F","n":6,"prop":0.00000479},{"year":1924,"sex":"F","n":7,"prop":0.0000054},{"year":1925,"sex":"F","n":6,"prop":0.00000475},{"year":1926,"sex":"F","n":7,"prop":0.00000569},{"year":1927,"sex":"F","n":5,"prop":0.00000404},{"year":1929,"sex":"F","n":7,"prop":0.00000605},{"year":1933,"sex":"F","n":6,"prop":0.00000574},{"year":1934,"sex":"F","n":7,"prop":0.00000647},{"year":1935,"sex":"F","n":89,"prop":0.0001},{"year":1936,"sex":"F","n":19,"prop":0},{"year":1937,"sex":"F","n":155,"prop":0.0001},{"year":1938,"sex":"F","n":47,"prop":0},{"year":1939,"sex":"F","n":34,"prop":0},{"year":1940,"sex":"F","n":19,"prop":0},{"year":1941,"sex":"F","n":24,"prop":0},{"year":1942,"sex":"F","n":17,"prop":0},{"year":1943,"sex":"F","n":14,"prop":0.00000975},{"year":1944,"sex":"F","n":11,"prop":0.00000805},{"year":1945,"sex":"F","n":11,"prop":0.00000817},{"year":1946,"sex":"F","n":6,"prop":0.00000372},{"year":1947,"sex":"F","n":11,"prop":0.00000605},{"year":1948,"sex":"F","n":11,"prop":0.00000631},{"year":1949,"sex":"F","n":16,"prop":0.00000911},{"year":1950,"sex":"F","n":9,"prop":0.00000512},{"year":1951,"sex":"F","n":10,"prop":0.00000541},{"year":1952,"sex":"F","n":13,"prop":0.00000683},{"year":1953,"sex":"F","n":12,"prop":0.00000622},{"year":1954,"sex":"F","n":14,"prop":0.00000703},{"year":1955,"sex":"F","n":16,"prop":0.00000798},{"year":1956,"sex":"F","n":17,"prop":0.00000826},{"year":1957,"sex":"F","n":9,"prop":0.00000429},{"year":1958,"sex":"F","n":17,"prop":0.00000823},{"year":1959,"sex":"F","n":13,"prop":0.00000625},{"year":1960,"sex":"F","n":14,"prop":0.00000673},{"year":1961,"sex":"F","n":19,"prop":0.00000915},{"year":1962,"sex":"F","n":14,"prop":0.00000691},{"year":1963,"sex":"F","n":6,"prop":0.00000302},{"year":1964,"sex":"F","n":14,"prop":0.00000715},{"year":1965,"sex":"F","n":7,"prop":0.00000383},{"year":1966,"sex":"F","n":6,"prop":0.00000342},{"year":1967,"sex":"F","n":8,"prop":0.00000466},{"year":1968,"sex":"F","n":9,"prop":0.00000526},{"year":1969,"sex":"F","n":7,"prop":0.00000397},{"year":1970,"sex":"F","n":6,"prop":0.00000328},{"year":1971,"sex":"F","n":6,"prop":0.00000342},{"year":1977,"sex":"F","n":8,"prop":0.00000486},{"year":1993,"sex":"F","n":5,"prop":0.00000254}]