[{"year":1928,"sex":"F","n":5,"prop":0.00000418},{"year":1929,"sex":"F","n":5,"prop":0.00000432},{"year":1929,"sex":"M","n":6,"prop":0.00000542},{"year":1930,"sex":"M","n":5,"prop":0.00000443},{"year":1931,"sex":"F","n":5,"prop":0.00000453},{"year":1932,"sex":"F","n":8,"prop":0.00000723},{"year":1933,"sex":"F","n":25,"prop":0},{"year":1934,"sex":"F","n":28,"prop":0},{"year":1935,"sex":"F","n":16,"prop":0},{"year":1936,"sex":"F","n":20,"prop":0},{"year":1937,"sex":"F","n":13,"prop":0},{"year":1937,"sex":"M","n":5,"prop":0.00000457},{"year":1938,"sex":"F","n":7,"prop":0.00000613},{"year":1939,"sex":"F","n":7,"prop":0.00000617},{"year":1939,"sex":"M","n":7,"prop":0.00000618},{"year":1940,"sex":"F","n":9,"prop":0.00000762},{"year":1941,"sex":"F","n":5,"prop":0.00000401},{"year":1942,"sex":"F","n":14,"prop":0},{"year":1946,"sex":"F","n":8,"prop":0.00000496},{"year":1946,"sex":"M","n":6,"prop":0.00000364},{"year":1947,"sex":"F","n":9,"prop":0.00000495},{"year":1948,"sex":"M","n":8,"prop":0.00000449},{"year":1949,"sex":"F","n":7,"prop":0.00000399},{"year":1950,"sex":"F","n":11,"prop":0.00000625},{"year":1951,"sex":"F","n":9,"prop":0.00000487},{"year":1952,"sex":"M","n":7,"prop":0.00000355},{"year":1953,"sex":"F","n":8,"prop":0.00000415},{"year":1954,"sex":"F","n":5,"prop":0.00000251},{"year":1955,"sex":"F","n":11,"prop":0.00000549},{"year":1957,"sex":"F","n":8,"prop":0.00000381},{"year":1957,"sex":"M","n":7,"prop":0.0000032},{"year":1959,"sex":"F","n":5,"prop":0.00000241},{"year":1959,"sex":"M","n":8,"prop":0.00000369},{"year":1960,"sex":"M","n":5,"prop":0.00000231},{"year":1965,"sex":"M","n":6,"prop":0.00000317},{"year":2005,"sex":"M","n":5,"prop":0.00000235},{"year":2015,"sex":"M","n":6,"prop":0.00000294}]