[{"year":1881,"sex":"M","n":5,"prop":0},{"year":1908,"sex":"M","n":5,"prop":0},{"year":1913,"sex":"M","n":7,"prop":0},{"year":1914,"sex":"M","n":5,"prop":0.00000732},{"year":1915,"sex":"M","n":6,"prop":0.00000681},{"year":1916,"sex":"M","n":6,"prop":0.0000065},{"year":1918,"sex":"M","n":8,"prop":0.00000763},{"year":1919,"sex":"M","n":8,"prop":0.00000788},{"year":1920,"sex":"M","n":6,"prop":0.00000545},{"year":1921,"sex":"M","n":8,"prop":0.00000703},{"year":1922,"sex":"M","n":5,"prop":0.00000444},{"year":1924,"sex":"M","n":7,"prop":0.00000599},{"year":1925,"sex":"M","n":7,"prop":0.00000608},{"year":1926,"sex":"M","n":9,"prop":0.00000786},{"year":1927,"sex":"M","n":6,"prop":0.00000516},{"year":1928,"sex":"M","n":6,"prop":0.00000526},{"year":1929,"sex":"M","n":6,"prop":0.00000542},{"year":1940,"sex":"M","n":7,"prop":0.0000059},{"year":1945,"sex":"M","n":6,"prop":0.00000438},{"year":1948,"sex":"M","n":7,"prop":0.00000393},{"year":1950,"sex":"M","n":6,"prop":0.0000033},{"year":1957,"sex":"M","n":5,"prop":0.00000229},{"year":1977,"sex":"M","n":6,"prop":0.00000351},{"year":2003,"sex":"M","n":6,"prop":0.00000286},{"year":2004,"sex":"M","n":6,"prop":0.00000284},{"year":2005,"sex":"M","n":6,"prop":0.00000282},{"year":2006,"sex":"M","n":7,"prop":0.0000032},{"year":2007,"sex":"M","n":5,"prop":0.00000226},{"year":2008,"sex":"M","n":10,"prop":0.00000459},{"year":2009,"sex":"M","n":10,"prop":0.00000472},{"year":2010,"sex":"M","n":7,"prop":0.00000341},{"year":2011,"sex":"M","n":12,"prop":0.00000592},{"year":2012,"sex":"M","n":6,"prop":0.00000296},{"year":2013,"sex":"M","n":9,"prop":0.00000446},{"year":2014,"sex":"M","n":14,"prop":0.00000685},{"year":2015,"sex":"M","n":9,"prop":0.00000442},{"year":2016,"sex":"F","n":5,"prop":0.00000259},{"year":2016,"sex":"M","n":14,"prop":0.00000694},{"year":2017,"sex":"F","n":5,"prop":0.00000267},{"year":2017,"sex":"M","n":16,"prop":0.00000815}]