[{"year":1996,"sex":"F","n":5,"prop":0.00000261},{"year":1997,"sex":"F","n":5,"prop":0.00000262},{"year":1999,"sex":"F","n":6,"prop":0.00000308},{"year":2000,"sex":"F","n":5,"prop":0.00000251},{"year":2001,"sex":"F","n":9,"prop":0.00000455},{"year":2002,"sex":"F","n":10,"prop":0.00000507},{"year":2003,"sex":"F","n":13,"prop":0.00000648},{"year":2004,"sex":"F","n":21,"prop":0},{"year":2005,"sex":"F","n":35,"prop":0},{"year":2006,"sex":"F","n":45,"prop":0},{"year":2007,"sex":"F","n":57,"prop":0},{"year":2008,"sex":"F","n":71,"prop":0},{"year":2009,"sex":"F","n":82,"prop":0},{"year":2009,"sex":"M","n":6,"prop":0.00000283},{"year":2010,"sex":"F","n":107,"prop":0.0001},{"year":2010,"sex":"M","n":8,"prop":0.0000039},{"year":2011,"sex":"F","n":141,"prop":0.0001},{"year":2011,"sex":"M","n":14,"prop":0.0000069},{"year":2012,"sex":"F","n":187,"prop":0.0001},{"year":2012,"sex":"M","n":5,"prop":0.00000247},{"year":2013,"sex":"F","n":176,"prop":0.0001},{"year":2013,"sex":"M","n":11,"prop":0.00000545},{"year":2014,"sex":"F","n":184,"prop":0.0001},{"year":2014,"sex":"M","n":9,"prop":0.0000044},{"year":2015,"sex":"F","n":185,"prop":0.0001},{"year":2015,"sex":"M","n":6,"prop":0.00000294},{"year":2016,"sex":"F","n":207,"prop":0.0001},{"year":2016,"sex":"M","n":9,"prop":0.00000446},{"year":2017,"sex":"F","n":198,"prop":0.0001},{"year":2017,"sex":"M","n":8,"prop":0.00000407}]