[{"year":1880,"sex":"M","n":25,"prop":0.0002},{"year":1881,"sex":"M","n":35,"prop":0.0003},{"year":1882,"sex":"M","n":31,"prop":0.0003},{"year":1883,"sex":"M","n":26,"prop":0.0002},{"year":1884,"sex":"M","n":21,"prop":0.0002},{"year":1885,"sex":"M","n":34,"prop":0.0003},{"year":1886,"sex":"M","n":23,"prop":0.0002},{"year":1887,"sex":"M","n":18,"prop":0.0002},{"year":1888,"sex":"M","n":30,"prop":0.0002},{"year":1889,"sex":"M","n":27,"prop":0.0002},{"year":1890,"sex":"M","n":15,"prop":0.0001},{"year":1891,"sex":"M","n":22,"prop":0.0002},{"year":1892,"sex":"M","n":29,"prop":0.0002},{"year":1893,"sex":"M","n":15,"prop":0.0001},{"year":1894,"sex":"M","n":14,"prop":0.0001},{"year":1895,"sex":"M","n":18,"prop":0.0001},{"year":1896,"sex":"M","n":11,"prop":0.0001},{"year":1897,"sex":"M","n":19,"prop":0.0002},{"year":1898,"sex":"M","n":14,"prop":0.0001},{"year":1899,"sex":"M","n":11,"prop":0.0001},{"year":1900,"sex":"M","n":27,"prop":0.0002},{"year":1901,"sex":"M","n":15,"prop":0.0001},{"year":1902,"sex":"M","n":10,"prop":0.0001},{"year":1903,"sex":"M","n":18,"prop":0.0001},{"year":1904,"sex":"M","n":14,"prop":0.0001},{"year":1905,"sex":"M","n":17,"prop":0.0001},{"year":1906,"sex":"M","n":17,"prop":0.0001},{"year":1907,"sex":"M","n":20,"prop":0.0001},{"year":1908,"sex":"M","n":20,"prop":0.0001},{"year":1909,"sex":"M","n":23,"prop":0.0001},{"year":1910,"sex":"M","n":15,"prop":0.0001},{"year":1911,"sex":"M","n":22,"prop":0.0001},{"year":1912,"sex":"M","n":41,"prop":0.0001},{"year":1913,"sex":"M","n":66,"prop":0.0001},{"year":1914,"sex":"M","n":67,"prop":0.0001},{"year":1915,"sex":"M","n":80,"prop":0.0001},{"year":1916,"sex":"M","n":84,"prop":0.0001},{"year":1917,"sex":"M","n":81,"prop":0.0001},{"year":1918,"sex":"M","n":100,"prop":0.0001},{"year":1919,"sex":"M","n":86,"prop":0.0001},{"year":1920,"sex":"M","n":109,"prop":0.0001},{"year":1921,"sex":"M","n":109,"prop":0.0001},{"year":1922,"sex":"M","n":95,"prop":0.0001},{"year":1923,"sex":"M","n":94,"prop":0.0001},{"year":1924,"sex":"M","n":83,"prop":0.0001},{"year":1925,"sex":"M","n":96,"prop":0.0001},{"year":1926,"sex":"M","n":82,"prop":0.0001},{"year":1927,"sex":"M","n":68,"prop":0.0001},{"year":1928,"sex":"M","n":74,"prop":0.0001},{"year":1929,"sex":"M","n":64,"prop":0.0001},{"year":1930,"sex":"M","n":55,"prop":0},{"year":1931,"sex":"M","n":56,"prop":0.0001},{"year":1932,"sex":"M","n":66,"prop":0.0001},{"year":1933,"sex":"M","n":70,"prop":0.0001},{"year":1934,"sex":"M","n":71,"prop":0.0001},{"year":1935,"sex":"M","n":56,"prop":0.0001},{"year":1936,"sex":"M","n":52,"prop":0},{"year":1937,"sex":"M","n":60,"prop":0.0001},{"year":1938,"sex":"M","n":65,"prop":0.0001},{"year":1939,"sex":"M","n":61,"prop":0.0001},{"year":1940,"sex":"M","n":57,"prop":0},{"year":1941,"sex":"M","n":70,"prop":0.0001},{"year":1942,"sex":"M","n":82,"prop":0.0001},{"year":1943,"sex":"M","n":84,"prop":0.0001},{"year":1944,"sex":"M","n":63,"prop":0},{"year":1945,"sex":"M","n":77,"prop":0.0001},{"year":1946,"sex":"M","n":90,"prop":0.0001},{"year":1947,"sex":"M","n":91,"prop":0},{"year":1948,"sex":"M","n":99,"prop":0.0001},{"year":1949,"sex":"M","n":139,"prop":0.0001},{"year":1950,"sex":"M","n":132,"prop":0.0001},{"year":1951,"sex":"M","n":119,"prop":0.0001},{"year":1952,"sex":"M","n":129,"prop":0.0001},{"year":1953,"sex":"M","n":174,"prop":0.0001},{"year":1954,"sex":"M","n":217,"prop":0.0001},{"year":1955,"sex":"M","n":215,"prop":0.0001},{"year":1956,"sex":"M","n":247,"prop":0.0001},{"year":1957,"sex":"M","n":260,"prop":0.0001},{"year":1958,"sex":"M","n":315,"prop":0.0001},{"year":1959,"sex":"M","n":292,"prop":0.0001},{"year":1960,"sex":"M","n":341,"prop":0.0002},{"year":1961,"sex":"M","n":330,"prop":0.0002},{"year":1962,"sex":"M","n":315,"prop":0.0001},{"year":1963,"sex":"M","n":292,"prop":0.0001},{"year":1964,"sex":"M","n":346,"prop":0.0002},{"year":1965,"sex":"M","n":325,"prop":0.0002},{"year":1966,"sex":"M","n":343,"prop":0.0002},{"year":1967,"sex":"F","n":5,"prop":0.00000291},{"year":1967,"sex":"M","n":395,"prop":0.0002},{"year":1968,"sex":"M","n":525,"prop":0.0003},{"year":1969,"sex":"M","n":582,"prop":0.0003},{"year":1970,"sex":"M","n":793,"prop":0.0004},{"year":1971,"sex":"M","n":780,"prop":0.0004},{"year":1972,"sex":"F","n":7,"prop":0.00000434},{"year":1972,"sex":"M","n":869,"prop":0.0005},{"year":1973,"sex":"M","n":1138,"prop":0.0007},{"year":1974,"sex":"F","n":8,"prop":0.00000511},{"year":1974,"sex":"M","n":1412,"prop":0.0009},{"year":1975,"sex":"F","n":12,"prop":0.00000769},{"year":1975,"sex":"M","n":1869,"prop":0.0012},{"year":1976,"sex":"F","n":9,"prop":0.00000573},{"year":1976,"sex":"M","n":2099,"prop":0.0013},{"year":1977,"sex":"F","n":16,"prop":0.00000973},{"year":1977,"sex":"M","n":2288,"prop":0.0013},{"year":1978,"sex":"F","n":17,"prop":0},{"year":1978,"sex":"M","n":2505,"prop":0.0015},{"year":1979,"sex":"F","n":16,"prop":0.00000929},{"year":1979,"sex":"M","n":2838,"prop":0.0016},{"year":1980,"sex":"F","n":16,"prop":0.00000899},{"year":1980,"sex":"M","n":3050,"prop":0.0016},{"year":1981,"sex":"F","n":33,"prop":0},{"year":1981,"sex":"M","n":3138,"prop":0.0017},{"year":1982,"sex":"F","n":20,"prop":0},{"year":1982,"sex":"M","n":2910,"prop":0.0015},{"year":1983,"sex":"F","n":16,"prop":0.00000894},{"year":1983,"sex":"M","n":2858,"prop":0.0015},{"year":1984,"sex":"F","n":20,"prop":0},{"year":1984,"sex":"M","n":2913,"prop":0.0016},{"year":1985,"sex":"F","n":19,"prop":0},{"year":1985,"sex":"M","n":2820,"prop":0.0015},{"year":1986,"sex":"F","n":21,"prop":0},{"year":1986,"sex":"M","n":2978,"prop":0.0016},{"year":1987,"sex":"F","n":14,"prop":0.00000747},{"year":1987,"sex":"M","n":3339,"prop":0.0017},{"year":1988,"sex":"F","n":19,"prop":0.00000988},{"year":1988,"sex":"M","n":3491,"prop":0.0017},{"year":1989,"sex":"F","n":11,"prop":0.00000552},{"year":1989,"sex":"M","n":3633,"prop":0.0017},{"year":1990,"sex":"F","n":11,"prop":0.00000536},{"year":1990,"sex":"M","n":3560,"prop":0.0017},{"year":1991,"sex":"F","n":16,"prop":0.00000787},{"year":1991,"sex":"M","n":3806,"prop":0.0018},{"year":1992,"sex":"F","n":13,"prop":0.00000649},{"year":1992,"sex":"M","n":3911,"prop":0.0019},{"year":1993,"sex":"F","n":14,"prop":0.0000071},{"year":1993,"sex":"M","n":4060,"prop":0.002},{"year":1994,"sex":"F","n":7,"prop":0.00000359},{"year":1994,"sex":"M","n":4133,"prop":0.002},{"year":1995,"sex":"F","n":8,"prop":0.00000416},{"year":1995,"sex":"M","n":3912,"prop":0.0019},{"year":1996,"sex":"F","n":14,"prop":0.0000073},{"year":1996,"sex":"M","n":3886,"prop":0.0019},{"year":1997,"sex":"F","n":8,"prop":0.00000419},{"year":1997,"sex":"M","n":4043,"prop":0.002},{"year":1998,"sex":"F","n":6,"prop":0.0000031},{"year":1998,"sex":"M","n":4586,"prop":0.0023},{"year":1999,"sex":"F","n":6,"prop":0.00000308},{"year":1999,"sex":"M","n":6303,"prop":0.0031},{"year":2000,"sex":"F","n":8,"prop":0.00000401},{"year":2000,"sex":"M","n":6717,"prop":0.0032},{"year":2001,"sex":"F","n":9,"prop":0.00000455},{"year":2001,"sex":"M","n":6223,"prop":0.003},{"year":2002,"sex":"F","n":11,"prop":0.00000557},{"year":2002,"sex":"M","n":5738,"prop":0.0028},{"year":2003,"sex":"F","n":8,"prop":0.00000399},{"year":2003,"sex":"M","n":5255,"prop":0.0025},{"year":2004,"sex":"F","n":28,"prop":0},{"year":2004,"sex":"M","n":5185,"prop":0.0025},{"year":2005,"sex":"F","n":7,"prop":0.00000345},{"year":2005,"sex":"M","n":4711,"prop":0.0022},{"year":2006,"sex":"F","n":13,"prop":0.00000622},{"year":2006,"sex":"M","n":4325,"prop":0.002},{"year":2007,"sex":"F","n":9,"prop":0.00000426},{"year":2007,"sex":"M","n":3768,"prop":0.0017},{"year":2008,"sex":"F","n":5,"prop":0.0000024},{"year":2008,"sex":"M","n":3281,"prop":0.0015},{"year":2009,"sex":"M","n":2941,"prop":0.0014},{"year":2010,"sex":"M","n":2377,"prop":0.0012},{"year":2011,"sex":"F","n":5,"prop":0.00000258},{"year":2011,"sex":"M","n":2092,"prop":0.001},{"year":2012,"sex":"M","n":1811,"prop":0.0009},{"year":2013,"sex":"F","n":5,"prop":0.0000026},{"year":2013,"sex":"M","n":1592,"prop":0.0008},{"year":2014,"sex":"F","n":5,"prop":0.00000256},{"year":2014,"sex":"M","n":1501,"prop":0.0007},{"year":2015,"sex":"M","n":1340,"prop":0.0007},{"year":2016,"sex":"M","n":1159,"prop":0.0006},{"year":2017,"sex":"M","n":1051,"prop":0.0005}]