[{"year":1960,"sex":"F","n":6,"prop":0.00000288},{"year":1961,"sex":"F","n":8,"prop":0.00000385},{"year":1962,"sex":"F","n":9,"prop":0.00000444},{"year":1963,"sex":"F","n":6,"prop":0.00000302},{"year":1964,"sex":"F","n":7,"prop":0.00000358},{"year":1965,"sex":"F","n":5,"prop":0.00000274},{"year":2005,"sex":"F","n":5,"prop":0.00000247},{"year":2006,"sex":"F","n":10,"prop":0.00000479},{"year":2007,"sex":"F","n":25,"prop":0},{"year":2008,"sex":"F","n":35,"prop":0},{"year":2009,"sex":"F","n":99,"prop":0},{"year":2010,"sex":"F","n":161,"prop":0.0001},{"year":2011,"sex":"F","n":192,"prop":0.0001},{"year":2012,"sex":"F","n":160,"prop":0.0001},{"year":2013,"sex":"F","n":171,"prop":0.0001},{"year":2014,"sex":"F","n":148,"prop":0.0001},{"year":2015,"sex":"F","n":141,"prop":0.0001},{"year":2016,"sex":"F","n":127,"prop":0.0001},{"year":2017,"sex":"F","n":146,"prop":0.0001}]