[{"year":1905,"n":8,"prop":0.0001},{"year":1907,"n":5,"prop":0},{"year":1913,"n":7,"prop":0},{"year":1914,"n":6,"prop":0.00000878},{"year":1915,"n":13,"prop":0},{"year":1917,"n":5,"prop":0.00000521},{"year":1918,"n":6,"prop":0.00000572},{"year":1919,"n":5,"prop":0.00000492},{"year":1920,"n":6,"prop":0.00000545},{"year":1921,"n":5,"prop":0.00000439},{"year":1922,"n":10,"prop":0.00000889},{"year":1926,"n":6,"prop":0.00000524},{"year":1927,"n":6,"prop":0.00000516},{"year":1928,"n":9,"prop":0.00000789},{"year":1929,"n":8,"prop":0.00000722},{"year":1932,"n":5,"prop":0.00000465},{"year":1935,"n":5,"prop":0.00000468},{"year":1962,"n":5,"prop":0.00000238},{"year":1991,"n":5,"prop":0.00000236},{"year":1993,"n":5,"prop":0.00000242}]