[{"year":1976,"n":5,"prop":0.00000306},{"year":1978,"n":10,"prop":0.00000585},{"year":1979,"n":6,"prop":0.00000335},{"year":1981,"n":8,"prop":0.0000043},{"year":1982,"n":8,"prop":0.00000424},{"year":1983,"n":8,"prop":0.00000429},{"year":1984,"n":13,"prop":0.00000693},{"year":1985,"n":9,"prop":0.00000468},{"year":1986,"n":29,"prop":0},{"year":1987,"n":31,"prop":0},{"year":1988,"n":24,"prop":0},{"year":1989,"n":32,"prop":0},{"year":1990,"n":50,"prop":0},{"year":1991,"n":67,"prop":0},{"year":1992,"n":72,"prop":0},{"year":1993,"n":89,"prop":0},{"year":1994,"n":156,"prop":0.0001},{"year":1995,"n":197,"prop":0.0001},{"year":1996,"n":132,"prop":0.0001},{"year":1997,"n":118,"prop":0.0001},{"year":1998,"n":133,"prop":0.0001},{"year":1999,"n":102,"prop":0.0001},{"year":2000,"n":127,"prop":0.0001},{"year":2001,"n":129,"prop":0.0001},{"year":2002,"n":99,"prop":0},{"year":2003,"n":90,"prop":0},{"year":2004,"n":107,"prop":0.0001},{"year":2005,"n":89,"prop":0},{"year":2006,"n":101,"prop":0},{"year":2007,"n":94,"prop":0},{"year":2008,"n":92,"prop":0},{"year":2009,"n":73,"prop":0},{"year":2010,"n":68,"prop":0},{"year":2011,"n":55,"prop":0},{"year":2012,"n":179,"prop":0.0001},{"year":2013,"n":158,"prop":0.0001},{"year":2014,"n":106,"prop":0.0001},{"year":2015,"n":62,"prop":0},{"year":2016,"n":75,"prop":0},{"year":2017,"n":55,"prop":0}]